proxy_list/__init__.py
proxy_list/proxy_list.py
free_proxy_list-0.0.3.dist-info/METADATA
free_proxy_list-0.0.3.dist-info/WHEEL
free_proxy_list-0.0.3.dist-info/top_level.txt
free_proxy_list-0.0.3.dist-info/RECORD
