Metadata-Version: 2.1
Name: free-proxy-list
Version: 0.0.3
Summary: This package is to get free proxy ips and port number for scraping and for testing on proxy.
Home-page: https://github.com/meetsohail/proxy-list
Author: Sohail Ahmed
Author-email: meetsohail360@gmail.com
License: UNKNOWN
Keywords: proxy,server,scraping,request,python,selenium
Platform: UNKNOWN
Requires-Dist: requests
